minir/__init__.py
minir/ir.py
minir/onnx_to_tosa.py
minir/onnx_utils.py
minir/onnx_writer.py
minir/rewrite.py
minir/tosa_writer.py
minir/utils.py
minir-0.1.9.dist-info/licenses/LICENSE
minir-0.1.9.dist-info/METADATA
minir-0.1.9.dist-info/WHEEL
minir-0.1.9.dist-info/top_level.txt
minir-0.1.9.dist-info/RECORD
